qinum_xai/__init__.py
qinum_xai/xai_inspect_model.py
qinum_xai/xai_lime.py
qinum_xai/xai_shap.py
qinum_xai/xai_yolo.py
qinum_xai-0.1.8.dist-info/licenses/LICENSE
qinum_xai-0.1.8.dist-info/METADATA
qinum_xai-0.1.8.dist-info/WHEEL
qinum_xai-0.1.8.dist-info/top_level.txt
qinum_xai-0.1.8.dist-info/RECORD
