Metadata-Version: 2.4
Name: qinum_xai
Version: 0.1.8
Summary: Explainable AI (XAI) and YOLO visualization + layer inspection utilities
Home-page: https://qinum@dev.azure.com/qinum/RailAIxs/_git/Qinum_XAI
Author: Shivam Gupta
Author-email: s.gupta@qinum.com
License: MIT
Project-URL: Source, https://qinum@dev.azure.com/qinum/RailAIxs/_git/Qinum_XAI
Project-URL: Tracker, https://qinum@dev.azure.com/qinum/RailAIxs/_git/Qinum_XAI
Classifier: Development Status :: 4 - Beta
Classifier: Intended Audience :: Science/Research
Classifier: Topic :: Scientific/Engineering :: Artificial Intelligence
Classifier: License :: OSI Approved :: MIT License
Classifier: Programming Language :: Python :: 3.9
Classifier: Programming Language :: Python :: 3.10
Classifier: Programming Language :: Python :: 3.11
Classifier: Programming Language :: Python :: 3.12
Classifier: Programming Language :: Python :: 3.13
Classifier: Programming Language :: Python :: 3.14
Classifier: Operating System :: OS Independent
Requires-Python: >=3.9
License-File: LICENSE
Requires-Dist: torch
Requires-Dist: torchvision
Requires-Dist: ultralytics
Requires-Dist: grad-cam
Requires-Dist: opencv-python
Requires-Dist: numpy
Requires-Dist: matplotlib
Requires-Dist: tqdm
Requires-Dist: scikit-image
Requires-Dist: scikit-learn
Requires-Dist: lime
Requires-Dist: shap
Requires-Dist: ttach
Provides-Extra: dev
Requires-Dist: build; extra == "dev"
Requires-Dist: twine; extra == "dev"
Requires-Dist: pytest; extra == "dev"
Requires-Dist: black; extra == "dev"
Requires-Dist: isort; extra == "dev"
Dynamic: license-file
